macros/__init__.py
macros/models.py
macros/templatetags/__init__.py
macros/templatetags/macros.py
django_templates_macros-0.3.dist-info/AUTHORS
django_templates_macros-0.3.dist-info/LICENSE
django_templates_macros-0.3.dist-info/METADATA
django_templates_macros-0.3.dist-info/WHEEL
django_templates_macros-0.3.dist-info/top_level.txt
django_templates_macros-0.3.dist-info/RECORD
